scikit_learn_bench/CONST.py
scikit_learn_bench/Timeout.py
scikit_learn_bench/Timeout0.py
scikit_learn_bench/__init__.py
scikit_learn_bench/all_bench.py
scikit_learn_bench/cli.py
scikit_learn_bench/core.py
scikit_learn_bench/default_params.py
scikit_learn_bench/display.py
scikit_learn_bench/profiler.py
scikit_learn_bench-0.1.2.dist-info/licenses/LICENSE
scikit_learn_bench-0.1.2.dist-info/METADATA
scikit_learn_bench-0.1.2.dist-info/WHEEL
scikit_learn_bench-0.1.2.dist-info/entry_points.txt
scikit_learn_bench-0.1.2.dist-info/top_level.txt
scikit_learn_bench-0.1.2.dist-info/RECORD
