Metadata-Version: 2.4
Name: scikit_learn_bench
Version: 0.1.2
Summary: ML Benchmark used to compare platforms
Home-page: https://github.com/PierrickPochelu/scikit-learn-bench
Author: Pierrick Pochelu
Author-email: Pierrick Pochelu <pierrick.pochelu@gmail.com>
License: Apache-2.0
Project-URL: Homepage, https://ghttps://github.com/PierrickPochelu/scikit-learn-bench
Project-URL: Bug Tracker, https://github.com/PierrickPochelu/scikit-learn-bench/issues
Classifier: Programming Language :: Python :: 3
Classifier: Operating System :: OS Independent
Requires-Python: >=3.8
License-File: LICENSE
Dynamic: author
Dynamic: home-page
Dynamic: license-file
Dynamic: requires-python
